data/202211_correspondance_idbank_dimension.csv.gz
data/202211_liste_variables_modalites.csv.gz
data/naf2008-listes-completes-5-niveaux.csv.gz
pybdm_insee/__init__ .py
pybdm_insee/__main__.py
pybdm_insee/installs/__init__ .py
pybdm_insee/installs/poetry_install.py
pybdm_insee/py-insee.code-workspace
pybdm_insee/tools/__init__.py
pybdm_insee/tools/attrdict/__init__.py
pybdm_insee/tools/attrdict/default.py
pybdm_insee/tools/attrdict/dictionary.py
pybdm_insee/tools/attrdict/mapping.py
pybdm_insee/tools/attrdict/merge.py
pybdm_insee/tools/attrdict/mixins.py
pybdm_insee/tools/dataframes.py
pybdm_insee/tools/find.py
pybdm_insee/tools/insee.py
pybdm_insee/tools/processing.py
pybdm_insee-0.1.7.dist-info/entry_points.txt
pybdm_insee-0.1.7.dist-info/LICENSE
pybdm_insee-0.1.7.dist-info/WHEEL
pybdm_insee-0.1.7.dist-info/METADATA
pybdm_insee-0.1.7.dist-info/RECORD
