Metadata-Version: 2.1
Name: pybdm-insee
Version: 0.1.7
Summary: 
Author: Arno's Stuff
Author-email: bcda0276@gmail.com
Requires-Python: >=3.10,<4.0
Classifier: Programming Language :: Python :: 3
Classifier: Programming Language :: Python :: 3.10
Classifier: Programming Language :: Python :: 3.11
Provides-Extra: caching
Provides-Extra: spacy
Requires-Dist: click (>=8.1.3,<9.0.0)
Requires-Dist: colorama (>=0.4.6,<0.5.0)
Requires-Dist: lxml (>=4.9.1,<5.0.0)
Requires-Dist: pandas (>=1.5.1,<2.0.0)
Requires-Dist: requests (>=2.28.1,<3.0.0)
Requires-Dist: rich (>=12.6.0,<13.0.0)
Requires-Dist: spacy (>=3.4.3,<4.0.0); extra == "caching" or extra == "spacy"
